setup.cfg
setup.py
simulacrum/__init__.py
simulacrum/coltypes.py
simulacrum/dataset.py
simulacrum/simdata.py
simulacrum.egg-info/PKG-INFO
simulacrum.egg-info/SOURCES.txt
simulacrum.egg-info/dependency_links.txt
simulacrum.egg-info/not-zip-safe
simulacrum.egg-info/requires.txt
simulacrum.egg-info/top_level.txt