Metadata-Version: 1.1
Name: simulacrum
Version: 0.2.3
Summary: Create Pandas DataFrames of simulated data with columns following statistical distributions or categorical datatypes
Home-page: https://github.com/jbrambleDC/simulacrum
Author: Jordan Bramble
Author-email: jordanbramble@gmail.com
License: MIT
Download-URL: https://github.com/jbrambleDC/simulacrum/tarball/0.2.3
Keywords: simulation,data,data science
Platform: UNKNOWN
